{"cameraMode":{"drawMode":0,"name":"Shaded","section":"Shading Mode"},"sceneLighting":true,"audioPlay":false,"sceneViewState":{"m_AlwaysRefresh":false,"showFog":true,"showSkybox":true,"showFlares":true,"showImageEffects":true,"showParticleSystems":true,"showVisualEffectGraphs":true,"m_FxEnabled":true},"in2DMode":false,"pivot":{"x":4.632545471191406,"y":1.0453577041625977,"z":-23.539548873901368},"rotation":{"x":-0.39402714371681216,"y":0.4991387724876404,"z":-0.27235186100006106,"w":-0.7221140265464783},"size":14.584737777709961,"orthographic":false}